ttm.py
ttm-0.14.0.dist-info/entry_points.txt
ttm-0.14.0.dist-info/LICENSE
ttm-0.14.0.dist-info/WHEEL
ttm-0.14.0.dist-info/METADATA
ttm-0.14.0.dist-info/RECORD
