Metadata-Version: 2.1
Name: ttm
Version: 0.14.0
Summary: Tiny task manager for Linux, MacOS and Unix-like systems
Home-page: https://github.com/yuriescl/ttm
License: MIT
Author: Yuri Escalianti
Author-email: yuriescl@gmail.com
Requires-Python: >=3.8,<4.0
Classifier: License :: OSI Approved :: MIT License
Classifier: Programming Language :: Python :: 3
Classifier: Programming Language :: Python :: 3.8
Classifier: Programming Language :: Python :: 3.9
Classifier: Programming Language :: Python :: 3.10
Classifier: Programming Language :: Python :: 3.11
